setup.py
blueprint_decr/__init__.py
blueprint_decr.egg-info/PKG-INFO
blueprint_decr.egg-info/SOURCES.txt
blueprint_decr.egg-info/dependency_links.txt
blueprint_decr.egg-info/not-zip-safe
blueprint_decr.egg-info/requires.txt
blueprint_decr.egg-info/top_level.txt