Metadata-Version: 1.1
Name: blueprint-decr
Version: 0.1.1
Summary: UNKNOWN
Home-page: https://github.com/socrateslee/blueprint-decr
Author: Lichun
Author-email: UNKNOWN
License: MIT
Platform: UNKNOWN
Classifier: Environment :: Console
Classifier: Framework :: Flask
Classifier: Intended Audience :: Developers
Classifier: License :: OSI Approved :: MIT License
Classifier: Programming Language :: Python
